tcod/camera/__init__.py
tcod/camera/py.typed
tcod/camera/test_camera.py
tcod_camera-1.0.1.dist-info/LICENSE
tcod_camera-1.0.1.dist-info/WHEEL
tcod_camera-1.0.1.dist-info/METADATA
tcod_camera-1.0.1.dist-info/RECORD
