Metadata-Version: 2.1
Name: tcod-camera
Version: 1.0.1
Summary: Camera helper tools for 2D tile-based projects.
Author-email: Kyle Benesch <4b796c65+github@gmail.com>
Requires-Python: >=3.8
Classifier: Development Status :: 5 - Production/Stable
Classifier: Intended Audience :: Developers
Classifier: License :: OSI Approved :: MIT License
Classifier: Operating System :: OS Independent
Classifier: Programming Language :: Python :: 3
Classifier: Topic :: Software Development :: Libraries :: Python Modules
Classifier: Typing :: Typed
Requires-Dist: pytest >=7.2.0 ; extra == "test"
Requires-Dist: pytest-cov >=4.0.0 ; extra == "test"
Requires-Dist: mypy >=0.991 ; extra == "test"
Requires-Dist: attrs >=22.2.0 ; extra == "test"
Requires-Dist: numpy >=1.23.5 ; extra == "test"
Requires-Dist: tcod >=15.0.0 ; extra == "test"
Project-URL: Changelog, https://github.com/HexDecimal/python-tcod-camera/blob/main/CHANGELOG.md
Project-URL: Documentation, https://python-tcod-camera.readthedocs.io
Project-URL: Home, https://github.com/HexDecimal/python-tcod-camera
Project-URL: Source, https://github.com/HexDecimal/python-tcod-camera
Provides-Extra: test
